GetWeather/Main.py
GetWeather/__init__.py
WeatherPlug/Main.py
WeatherPlug/__init__.py
WeatherPlug-1.1.dist-info/METADATA
WeatherPlug-1.1.dist-info/WHEEL
WeatherPlug-1.1.dist-info/top_level.txt
WeatherPlug-1.1.dist-info/RECORD
