Metadata-Version: 2.1
Name: WeatherPlug
Version: 1.1
Requires-Dist: Requests >=2.31.0
